pacwrap/__init__.py
pacwrap/apt.py
pacwrap/cli.py
pacwrap/dnf.py
pacwrap/mkhandler.py
pacwrap/options.py
pacwrap/pacman.py
pacwrap/pkgmgr.py
pacwrap/py.typed
pacwrap/yum.py
pacwrap-0.6.0.dist-info/LICENSE
pacwrap-0.6.0.dist-info/METADATA
pacwrap-0.6.0.dist-info/WHEEL
pacwrap-0.6.0.dist-info/entry_points.txt
pacwrap-0.6.0.dist-info/RECORD
