Metadata-Version: 2.1
Name: pacwrap
Version: 0.6.0
Summary: Provides single interface to several common Linux package managers.
Home-page: https://github.com/wtfo-guru/pacwrap
License: MIT
Author: Quien Sabe
Author-email: qs5779@mail.com
Requires-Python: >=3.9.0,<4.0
Classifier: Development Status :: 4 - Beta
Classifier: Environment :: Console
Classifier: Intended Audience :: End Users/Desktop
Classifier: Intended Audience :: System Administrators
Classifier: License :: OSI Approved :: MIT License
Classifier: Operating System :: POSIX :: Linux
Classifier: Programming Language :: Python :: 3
Classifier: Programming Language :: Python :: 3.9
Classifier: Programming Language :: Python :: 3.10
Classifier: Programming Language :: Python :: 3.11
Classifier: Programming Language :: Python :: 3.12
Classifier: Programming Language :: Python :: 3 :: Only
Classifier: Topic :: Utilities
Classifier: Typing :: Typed
Requires-Dist: click (>=8.1.0,<9.0.0)
Requires-Dist: cmp-version (>=3.0.0,<4.0.0)
Requires-Dist: distro (>=1.9,<2.0)
Requires-Dist: wtforglib (>=1.0.0,<2.0.0)
Project-URL: Documentation, https://python-pacwrap.readthedocs.io/en/stable
